fabio/__init__.py
fabio/adscimage.py
fabio/dm3image.py
fabio/fabioutils.py
fabio/kcdimage.py
fabio/datIO.py
fabio/speimage.py
fabio/cbfimage.py
fabio/fit2dmaskimage.py
fabio/templateimage.py
fabio/openimage.py
fabio/fabioimage.py
fabio/numpyimage.py
fabio/nexus.py
fabio/tifimage.py
fabio/brukerimage.py
fabio/edfimage.py
fabio/fabioformats.py
fabio/fit2dspreadsheetimage.py
fabio/pilatusimage.py
fabio/xsdimage.py
fabio/HiPiCimage.py
fabio/hdf5image.py
fabio/pixiimage.py
fabio/limaimage.py
fabio/binaryimage.py
fabio/xcaliburimage.py
fabio/file_series.py
fabio/directories.py
fabio/bruker100image.py
fabio/esperantoimage.py
fabio/converters.py
fabio/readbytestream.py
fabio/mrcimage.py
fabio/eigerimage.py
fabio/sparseimage.py
fabio/_version.py
fabio/jpeg2kimage.py
fabio/pnmimage.py
fabio/OXDimage.py
fabio/GEimage.py
fabio/fit2dimage.py
fabio/dtrekimage.py
fabio/mar345image.py
fabio/mpaimage.py
fabio/raxisimage.py
fabio/jpegimage.py
fabio/marccdimage.py
fabio/TiffIO.py
fabio/test/__init__.py
fabio/test/test_compression.py
fabio/test/test_formats.py
fabio/test/test_tiffio.py
fabio/test/test_densification.py
fabio/test/test_filename_steps.py
fabio/test/test_fabio.py
fabio/test/test_fabio_convert.py
fabio/test/test_file_series.py
fabio/test/test_all_images.py
fabio/test/test_failing_files.py
fabio/test/test_utils_cli.py
fabio/test/testutils.py
fabio/test/test_io_limits.py
fabio/test/test_nexus.py
fabio/test/test_all.py
fabio/test/test_agi_bitfield.py
fabio/test/profile_all.py
fabio/test/test_open_image.py
fabio/test/test_flat_binary.py
fabio/test/test_header_not_singleton.py
fabio/test/test_filenames.py
fabio/test/test_image_convert.py
fabio/test/test_frames.py
fabio/test/test_fabio_image.py
fabio/test/utilstest.py
fabio/test/test_open_header.py
fabio/test/codecs/__init__.py
fabio/test/codecs/test_oxdimage.py
fabio/test/codecs/test_tifimage.py
fabio/test/codecs/test_binaryimage.py
fabio-2023.4.1.dist-info/copyright
fabio-2023.4.1.dist-info/RECORD
fabio-2023.4.1.dist-info/entry_points.txt
fabio-2023.4.1.dist-info/WHEEL
fabio-2023.4.1.dist-info/METADATA
