Metadata-Version: 2.1
Name: fabio
Version: 2023.4.1
Summary: FabIO is an I/O library for images produced by 2D X-ray detectors and written in Python
Home-page: http://silx.org
Author: Erik Knudsen, Regis Perdreau, Gael Goret, Brian Pauw
Author-Email: Henning Sorensen <osho@fysik.dtu.dk>, Jonathan P. Wright <wright@esrf.fr>, Jérôme Kieffer <jerome.kieffer@esrf.fr>, Valentin Valls <valentin.valls@esrf.fr>
License: Format: http://www.debian.org/doc/packaging-manuals/copyright-format/1.0/
Classifier: Development Status :: 5 - Production/Stable
Classifier: Environment :: Console
Classifier: Intended Audience :: End Users/Desktop
Classifier: Intended Audience :: Developers
Classifier: Intended Audience :: Science/Research
Classifier: License :: OSI Approved :: MIT License
Classifier: Operating System :: MacOS :: MacOS X
Classifier: Operating System :: Microsoft :: Windows
Classifier: Operating System :: POSIX
Classifier: Programming Language :: C
Classifier: Programming Language :: Cython
Classifier: Programming Language :: Python
Classifier: Programming Language :: Python :: 3
Classifier: Programming Language :: Python :: Implementation :: CPython
Classifier: Topic :: Scientific/Engineering :: Chemistry
Classifier: Topic :: Scientific/Engineering :: Bio-Informatics
Classifier: Topic :: Scientific/Engineering :: Physics
Classifier: Topic :: Scientific/Engineering :: Visualization
Classifier: Topic :: Software Development :: Libraries :: Python Modules
Project-URL: Homepage, http://silx.org
Project-URL: Documentation, http://www.silx.org/doc/fabio/latest/
Project-URL: Source, https://github.com/silx-kit/fabio
Project-URL: Download, https://github.com/silx-kit/fabio/releases
Project-URL: Tracker, https://github.com/silx-kit/fabio/issues
Requires-Python: >=3.7
Requires-Dist: numpy
